[
    {
        "CaseID": "{E52D7679-7E9C-4623-9CA7-AB704EF2465C}",
        "Description": "Interstate Transfer Order",
        "Version": 3,
        "MinorVersion": 0,
        "TaxType": "GST",
        "ChangedBy": "Microsoft",
        "Code": "GST HSN",
        "TaxEntity": "Transfer Line",
        "ParentUseCase": "",
        "ParentCaseId": "{00000000-0000-0000-0000-000000000000}",
        "PresentationOrder": 527,
        "Indent": 0,
        "Attributes": [
            {
                "Name": "HSN/SAC",
                "When": [
                    {
                        "ValueType": "Relation",
                        "Sequence": 0,
                        "Relation": {
                            "IsCurrentRecord": true,
                            "TableName": "Transfer Line"
                        }
                    }
                ]
            },
            {
                "Name": "GST Group Code",
                "When": [
                    {
                        "ValueType": "Relation",
                        "Sequence": 0,
                        "Relation": {
                            "IsCurrentRecord": true,
                            "TableName": "Transfer Line"
                        }
                    }
                ]
            }
        ],
        "RateColumns": [
            {
                "Name": "From State",
                "When": [
                    {
                        "ValueType": "Lookup",
                        "Sequence": 0,
                        "Lookup": {
                            "SourceType": "Table",
                            "TableName": "Location",
                            "TableFieldName": "State Code",
                            "Method": "First",
                            "TableFilters": [
                                {
                                    "FiterFieldName": "Code",
                                    "FilterType": "Equals",
                                    "FilterValue": {
                                        "Type": "Lookup",
                                        "Lookup": {
                                            "SourceType": "Table",
                                            "TableName": "Transfer Header",
                                            "TableFieldName": "Transfer-from Code",
                                            "Method": "First",
                                            "TableFilters": [
                                                {
                                                    "FiterFieldName": "No.",
                                                    "FilterType": "Equals",
                                                    "FilterValue": {
                                                        "Type": "Lookup",
                                                        "Lookup": {
                                                            "SourceType": "Current Record",
                                                            "TableName": "Transfer Line",
                                                            "FieldName": "Document No."
                                                        }
                                                    }
                                                }
                                            ]
                                        }
                                    }
                                }
                            ]
                        }
                    }
                ]
            },
            {
                "Name": "Location State Code",
                "When": [
                    {
                        "ValueType": "Lookup",
                        "Sequence": 0,
                        "Lookup": {
                            "SourceType": "Table",
                            "TableName": "Location",
                            "TableFieldName": "State Code",
                            "Method": "First",
                            "TableFilters": [
                                {
                                    "FiterFieldName": "Code",
                                    "FilterType": "Equals",
                                    "FilterValue": {
                                        "Type": "Lookup",
                                        "Lookup": {
                                            "SourceType": "Table",
                                            "TableName": "Transfer Header",
                                            "TableFieldName": "Transfer-to Code",
                                            "Method": "First",
                                            "TableFilters": [
                                                {
                                                    "FiterFieldName": "No.",
                                                    "FilterType": "Equals",
                                                    "FilterValue": {
                                                        "Type": "Lookup",
                                                        "Lookup": {
                                                            "SourceType": "Current Record",
                                                            "TableName": "Transfer Line",
                                                            "FieldName": "Document No."
                                                        }
                                                    }
                                                }
                                            ]
                                        }
                                    }
                                }
                            ]
                        }
                    }
                ]
            },
            {
                "Name": "Date",
                "When": [
                    {
                        "ValueType": "Lookup",
                        "Sequence": 0,
                        "Lookup": {
                            "SourceType": "Table",
                            "TableName": "Transfer Header",
                            "TableFieldName": "Posting Date",
                            "Method": "First",
                            "TableFilters": [
                                {
                                    "FiterFieldName": "No.",
                                    "FilterType": "Equals",
                                    "FilterValue": {
                                        "Type": "Lookup",
                                        "Lookup": {
                                            "SourceType": "Current Record",
                                            "TableName": "Transfer Line",
                                            "FieldName": "Document No."
                                        }
                                    }
                                }
                            ]
                        }
                    }
                ]
            }
        ],
        "ComputationVariables": [],
        "ComputationScript": [],
        "PostingVariables": [],
        "PostingScript": [],
        "Components": [
            {
                "ComponentName": "IGST",
                "Sequence": 0,
                "Formula": {
                    "VariableName": "IGST",
                    "Expression": "{Amount}*{IGSTPer}/100",
                    "Tokens": [
                        {
                            "TokenName": "{Amount}",
                            "TokenValue": {
                                "Type": "Lookup",
                                "Lookup": {
                                    "SourceType": "Current Record",
                                    "TableName": "Transfer Line",
                                    "FieldName": "Amount"
                                }
                            }
                        },
                        {
                            "TokenName": "{IGSTPer}",
                            "TokenValue": {
                                "Type": "Lookup",
                                "Lookup": {
                                    "SourceType": "Component Percent",
                                    "ComponentName": "IGST"
                                }
                            }
                        }
                    ]
                }
            }
        ],
        "Condition": {
            "Body": [
                {
                    "Operator": " ",
                    "ConditionType": "Equals",
                    "LHS": {
                        "Lookup": {
                            "SourceType": "Current Record",
                            "TableName": "Transfer Line",
                            "FieldName": "Exempted"
                        }
                    },
                    "RHS": {
                        "Type": "Constant",
                        "Value": ""
                    }
                },
                {
                    "Operator": "and",
                    "ConditionType": "Not Equals",
                    "LHS": {
                        "Lookup": {
                            "SourceType": "Table",
                            "TableName": "Location",
                            "TableFieldName": "State Code",
                            "Method": "First",
                            "TableFilters": [
                                {
                                    "FiterFieldName": "Code",
                                    "FilterType": "Equals",
                                    "FilterValue": {
                                        "Type": "Lookup",
                                        "Lookup": {
                                            "SourceType": "Table",
                                            "TableName": "Transfer Header",
                                            "TableFieldName": "Transfer-from Code",
                                            "Method": "First",
                                            "TableFilters": [
                                                {
                                                    "FiterFieldName": "No.",
                                                    "FilterType": "Equals",
                                                    "FilterValue": {
                                                        "Type": "Lookup",
                                                        "Lookup": {
                                                            "SourceType": "Current Record",
                                                            "TableName": "Transfer Line",
                                                            "FieldName": "Document No."
                                                        }
                                                    }
                                                }
                                            ]
                                        }
                                    }
                                }
                            ]
                        }
                    },
                    "RHS": {
                        "Type": "Lookup",
                        "Lookup": {
                            "SourceType": "Table",
                            "TableName": "Location",
                            "TableFieldName": "State Code",
                            "Method": "First",
                            "TableFilters": [
                                {
                                    "FiterFieldName": "Code",
                                    "FilterType": "Equals",
                                    "FilterValue": {
                                        "Type": "Lookup",
                                        "Lookup": {
                                            "SourceType": "Table",
                                            "TableName": "Transfer Header",
                                            "TableFieldName": "Transfer-to Code",
                                            "Method": "First",
                                            "TableFilters": [
                                                {
                                                    "FiterFieldName": "No.",
                                                    "FilterType": "Equals",
                                                    "FilterValue": {
                                                        "Type": "Lookup",
                                                        "Lookup": {
                                                            "SourceType": "Current Record",
                                                            "TableName": "Transfer Line",
                                                            "FieldName": "Document No."
                                                        }
                                                    }
                                                }
                                            ]
                                        }
                                    }
                                }
                            ]
                        }
                    }
                },
                {
                    "Operator": "and",
                    "ConditionType": "Equals",
                    "LHS": {
                        "Lookup": {
                            "SourceType": "Table",
                            "TableName": "Location",
                            "TableFieldName": "Bonded warehouse",
                            "Method": "First",
                            "TableFilters": [
                                {
                                    "FiterFieldName": "Code",
                                    "FilterType": "Equals",
                                    "FilterValue": {
                                        "Type": "Lookup",
                                        "Lookup": {
                                            "SourceType": "Table",
                                            "TableName": "Transfer Header",
                                            "TableFieldName": "Transfer-from Code",
                                            "Method": "First",
                                            "TableFilters": [
                                                {
                                                    "FiterFieldName": "No.",
                                                    "FilterType": "Equals",
                                                    "FilterValue": {
                                                        "Type": "Lookup",
                                                        "Lookup": {
                                                            "SourceType": "Current Record",
                                                            "TableName": "Transfer Line",
                                                            "FieldName": "Document No."
                                                        }
                                                    }
                                                }
                                            ]
                                        }
                                    }
                                }
                            ]
                        }
                    },
                    "RHS": {
                        "Type": "Constant",
                        "Value": ""
                    }
                },
                {
                    "Operator": "and",
                    "ConditionType": "Not Equals",
                    "LHS": {
                        "Lookup": {
                            "SourceType": "Current Record",
                            "TableName": "Transfer Line",
                            "FieldName": "GST Group Code"
                        }
                    },
                    "RHS": {
                        "Type": "Constant",
                        "Value": ""
                    }
                },
                {
                    "Operator": "and",
                    "ConditionType": "Not Equals",
                    "LHS": {
                        "Lookup": {
                            "SourceType": "Current Record",
                            "TableName": "Transfer Line",
                            "FieldName": "HSN/SAC Code"
                        }
                    },
                    "RHS": {
                        "Type": "Constant",
                        "Value": ""
                    }
                }
            ]
        }
    }
]