<?xml version="1.0" encoding="utf-8"?>
<PermissionSets>
  <PermissionSet RoleID="BC Perf. Toolkit" RoleName="Business Central Performance Toolkit">
    <Permission>
      <ObjectID>149000</ObjectID>
      <ObjectType>0</ObjectType>
      <ReadPermission>1</ReadPermission>
      <InsertPermission>1</InsertPermission>
      <ModifyPermission>1</ModifyPermission>
      <DeletePermission>1</DeletePermission>
      <ExecutePermission>0</ExecutePermission>
      <SecurityFilter />
    </Permission>
    <Permission>
      <ObjectID>149000</ObjectID>
      <ObjectType>1</ObjectType>
      <ReadPermission>0</ReadPermission>
      <InsertPermission>0</InsertPermission>
      <ModifyPermission>0</ModifyPermission>
      <DeletePermission>0</DeletePermission>
      <ExecutePermission>1</ExecutePermission>
      <SecurityFilter />
    </Permission>
    <Permission>
      <ObjectID>149002</ObjectID>
      <ObjectType>0</ObjectType>
      <ReadPermission>1</ReadPermission>
      <InsertPermission>1</InsertPermission>
      <ModifyPermission>1</ModifyPermission>
      <DeletePermission>1</DeletePermission>
      <ExecutePermission>0</ExecutePermission>
      <SecurityFilter />
    </Permission>
    <Permission>
      <ObjectID>149002</ObjectID>
      <ObjectType>1</ObjectType>
      <ReadPermission>0</ReadPermission>
      <InsertPermission>0</InsertPermission>
      <ModifyPermission>0</ModifyPermission>
      <DeletePermission>0</DeletePermission>
      <ExecutePermission>1</ExecutePermission>
      <SecurityFilter />
    </Permission>
    <Permission>
      <ObjectID>149003</ObjectID>
      <ObjectType>0</ObjectType>
      <ReadPermission>1</ReadPermission>
      <InsertPermission>1</InsertPermission>
      <ModifyPermission>1</ModifyPermission>
      <DeletePermission>1</DeletePermission>
      <ExecutePermission>0</ExecutePermission>
      <SecurityFilter />
    </Permission>
    <Permission>
      <ObjectID>149003</ObjectID>
      <ObjectType>1</ObjectType>
      <ReadPermission>0</ReadPermission>
      <InsertPermission>0</InsertPermission>
      <ModifyPermission>0</ModifyPermission>
      <DeletePermission>0</DeletePermission>
      <ExecutePermission>1</ExecutePermission>
      <SecurityFilter />
    </Permission>
    <Permission>
      <ObjectID>149001</ObjectID>
      <ObjectType>0</ObjectType>
      <ReadPermission>1</ReadPermission>
      <InsertPermission>1</InsertPermission>
      <ModifyPermission>1</ModifyPermission>
      <DeletePermission>1</DeletePermission>
      <ExecutePermission>0</ExecutePermission>
      <SecurityFilter />
    </Permission>
    <Permission>
      <ObjectID>149001</ObjectID>
      <ObjectType>1</ObjectType>
      <ReadPermission>0</ReadPermission>
      <InsertPermission>0</InsertPermission>
      <ModifyPermission>0</ModifyPermission>
      <DeletePermission>0</DeletePermission>
      <ExecutePermission>1</ExecutePermission>
      <SecurityFilter />
    </Permission>
    <Permission>
      <ObjectID>149004</ObjectID>
      <ObjectType>5</ObjectType>
      <ReadPermission>0</ReadPermission>
      <InsertPermission>0</InsertPermission>
      <ModifyPermission>0</ModifyPermission>
      <DeletePermission>0</DeletePermission>
      <ExecutePermission>1</ExecutePermission>
      <SecurityFilter />
    </Permission>
    <Permission>
      <ObjectID>149005</ObjectID>
      <ObjectType>5</ObjectType>
      <ReadPermission>0</ReadPermission>
      <InsertPermission>0</InsertPermission>
      <ModifyPermission>0</ModifyPermission>
      <DeletePermission>0</DeletePermission>
      <ExecutePermission>1</ExecutePermission>
      <SecurityFilter />
    </Permission>
    <Permission>
      <ObjectID>149002</ObjectID>
      <ObjectType>5</ObjectType>
      <ReadPermission>0</ReadPermission>
      <InsertPermission>0</InsertPermission>
      <ModifyPermission>0</ModifyPermission>
      <DeletePermission>0</DeletePermission>
      <ExecutePermission>1</ExecutePermission>
      <SecurityFilter />
    </Permission>
    <Permission>
      <ObjectID>149020</ObjectID>
      <ObjectType>5</ObjectType>
      <ReadPermission>0</ReadPermission>
      <InsertPermission>0</InsertPermission>
      <ModifyPermission>0</ModifyPermission>
      <DeletePermission>0</DeletePermission>
      <ExecutePermission>1</ExecutePermission>
      <SecurityFilter />
    </Permission>
    <Permission>
      <ObjectID>149000</ObjectID>
      <ObjectType>5</ObjectType>
      <ReadPermission>0</ReadPermission>
      <InsertPermission>0</InsertPermission>
      <ModifyPermission>0</ModifyPermission>
      <DeletePermission>0</DeletePermission>
      <ExecutePermission>1</ExecutePermission>
      <SecurityFilter />
    </Permission>
    <Permission>
      <ObjectID>149003</ObjectID>
      <ObjectType>5</ObjectType>
      <ReadPermission>0</ReadPermission>
      <InsertPermission>0</InsertPermission>
      <ModifyPermission>0</ModifyPermission>
      <DeletePermission>0</DeletePermission>
      <ExecutePermission>1</ExecutePermission>
      <SecurityFilter />
    </Permission>
    <Permission>
      <ObjectID>149004</ObjectID>
      <ObjectType>8</ObjectType>
      <ReadPermission>0</ReadPermission>
      <InsertPermission>0</InsertPermission>
      <ModifyPermission>0</ModifyPermission>
      <DeletePermission>0</DeletePermission>
      <ExecutePermission>1</ExecutePermission>
      <SecurityFilter />
    </Permission>
    <Permission>
      <ObjectID>149003</ObjectID>
      <ObjectType>8</ObjectType>
      <ReadPermission>0</ReadPermission>
      <InsertPermission>0</InsertPermission>
      <ModifyPermission>0</ModifyPermission>
      <DeletePermission>0</DeletePermission>
      <ExecutePermission>1</ExecutePermission>
      <SecurityFilter />
    </Permission>
    <Permission>
      <ObjectID>149005</ObjectID>
      <ObjectType>8</ObjectType>
      <ReadPermission>0</ReadPermission>
      <InsertPermission>0</InsertPermission>
      <ModifyPermission>0</ModifyPermission>
      <DeletePermission>0</DeletePermission>
      <ExecutePermission>1</ExecutePermission>
      <SecurityFilter />
    </Permission>
    <Permission>
      <ObjectID>149009</ObjectID>
      <ObjectType>8</ObjectType>
      <ReadPermission>0</ReadPermission>
      <InsertPermission>0</InsertPermission>
      <ModifyPermission>0</ModifyPermission>
      <DeletePermission>0</DeletePermission>
      <ExecutePermission>1</ExecutePermission>
      <SecurityFilter />
    </Permission>
    <Permission>
      <ObjectID>149002</ObjectID>
      <ObjectType>8</ObjectType>
      <ReadPermission>0</ReadPermission>
      <InsertPermission>0</InsertPermission>
      <ModifyPermission>0</ModifyPermission>
      <DeletePermission>0</DeletePermission>
      <ExecutePermission>1</ExecutePermission>
      <SecurityFilter />
    </Permission>
    <Permission>
      <ObjectID>149001</ObjectID>
      <ObjectType>8</ObjectType>
      <ReadPermission>0</ReadPermission>
      <InsertPermission>0</InsertPermission>
      <ModifyPermission>0</ModifyPermission>
      <DeletePermission>0</DeletePermission>
      <ExecutePermission>1</ExecutePermission>
      <SecurityFilter />
    </Permission>
    <Permission>
      <ObjectID>149000</ObjectID>
      <ObjectType>8</ObjectType>
      <ReadPermission>0</ReadPermission>
      <InsertPermission>0</InsertPermission>
      <ModifyPermission>0</ModifyPermission>
      <DeletePermission>0</DeletePermission>
      <ExecutePermission>1</ExecutePermission>
      <SecurityFilter />
    </Permission>
    <Permission>
      <ObjectID>149001</ObjectID>
      <ObjectType>6</ObjectType>
      <ReadPermission>0</ReadPermission>
      <InsertPermission>0</InsertPermission>
      <ModifyPermission>0</ModifyPermission>
      <DeletePermission>0</DeletePermission>
      <ExecutePermission>1</ExecutePermission>
      <SecurityFilter />
    </Permission>
    <Permission>
      <ObjectID>149000</ObjectID>
      <ObjectType>6</ObjectType>
      <ReadPermission>0</ReadPermission>
      <InsertPermission>0</InsertPermission>
      <ModifyPermission>0</ModifyPermission>
      <DeletePermission>0</DeletePermission>
      <ExecutePermission>1</ExecutePermission>
      <SecurityFilter />
    </Permission>
  </PermissionSet>
</PermissionSets>